fact_lake/__init__.py
fact_lake/cli.py
fact_lake/config.py
fact_lake/projectors.py
fact_lake/server.py
fact_lake-0.0.4.dist-info/entry_points.txt
fact_lake-0.0.4.dist-info/LICENSE
fact_lake-0.0.4.dist-info/WHEEL
fact_lake-0.0.4.dist-info/METADATA
fact_lake-0.0.4.dist-info/RECORD
